README.md
setup.py
jabberwock/__init__.py
jabberwock/axlhandler.py
jabberwock/axlsql.py
jabberwock/configuration.py
jabberwock/exceptions.py
jabberwock/utils.py
jabberwock.egg-info/PKG-INFO
jabberwock.egg-info/SOURCES.txt
jabberwock.egg-info/dependency_links.txt
jabberwock.egg-info/requires.txt
jabberwock.egg-info/top_level.txt
jabberwock/ccm/__init__.py
jabberwock/ccm/abstracts.py
jabberwock/ccm/common.py
jabberwock/ccm/mixings.py
jabberwock/ccm/xtypes.py