Metadata-Version: 2.1
Name: jabberwock
Version: 0.7.1
Summary: Python library that helps with accessing Cisco Call Manager over the AXL interface
Home-page: https://github.com/kwroble/jabberwock
Author: Kyle Wroble
Author-email: kwroble@gmail.com
License: UNKNOWN
Platform: UNKNOWN
Classifier: Programming Language :: Python :: 3
Classifier: License :: OSI Approved :: Zope Public License
Classifier: Operating System :: OS Independent
